{
    "ClassName": "",
    "Chance": 1.0,
    "Quantity": {
        "Min": 0.0,
        "Max": 0.0
    },
    "Health": [],
    "InventoryAttachments": [
        {
            "SlotName": "Body",
            "Items": [
                {
                    "ClassName": "ManSuit_White",
                    "Chance": 1.0,
                    "Quantity": {
                        "Min": 0.0,
                        "Max": 0.0
                    },
                    "Health": [
                        {
                            "Min": 0.699999988079071,
                            "Max": 1.0,
                            "Zone": ""
                        }
                    ],
                    "InventoryAttachments": [],
                    "InventoryCargo": [],
                    "ConstructionPartsBuilt": []
                }
            ]
        },
        {
            "SlotName": "Eyewear",
            "Items": [
                {
                    "ClassName": "thinframesglasses",
                    "Chance": 1.0,
                    "Quantity": {
                        "Min": 0.0,
                        "Max": 0.0
                    },
                    "Health": [
                        {
                            "Min": 0.699999988079071,
                            "Max": 1.0,
                            "Zone": ""
                        }
                    ],
                    "InventoryAttachments": [],
                    "InventoryCargo": [],
                    "ConstructionPartsBuilt": []
                }
            ]
        },
        {
            "SlotName": "Legs",
            "Items": [
                {
                    "ClassName": "SlacksPants_White",
                    "Chance": 1.0,
                    "Quantity": {
                        "Min": 0.0,
                        "Max": 0.0
                    },
                    "Health": [
                        {
                            "Min": 0.699999988079071,
                            "Max": 1.0,
                            "Zone": ""
                        }
                    ],
                    "InventoryAttachments": [],
                    "InventoryCargo": [],
                    "ConstructionPartsBuilt": []
                }
            ]
        },
        {
            "SlotName": "Feet",
            "Items": [
                {
                    "ClassName": "DressShoes_White",
                    "Chance": 1.0,
                    "Quantity": {
                        "Min": 0.0,
                        "Max": 0.0
                    },
                    "Health": [
                        {
                            "Min": 0.699999988079071,
                            "Max": 1.0,
                            "Zone": ""
                        }
                    ],
                    "InventoryAttachments": [],
                    "InventoryCargo": [],
                    "ConstructionPartsBuilt": []
                }
            ]
        },
        {
            "SlotName": "Hands",
            "Items": [
                {
                    "ClassName": "TWP_Colt1911Holy",
                    "Chance": 1.0,
                    "Quantity": {
                        "Min": 0.0,
                        "Max": 0.0
                    },
                    "Health": [],
                    "InventoryAttachments": [],
                    "InventoryCargo": [],
                    "ConstructionPartsBuilt": []
                }
            ]
        }
    ],
    "InventoryCargo": [],
    "ConstructionPartsBuilt": []
}