{
    "ConfigVersion": 3,
    "ID": 25,
    "Type": 2,
    "Title": "25 - Neviditelné nebezpečí",
    "Descriptions": [
        "Zabij 5 škorpionů lopatou!"
    ],
    "ObjectiveText": "Zabij 5 škorpionů lopatou!",
    "PreQuest": 1,
    "FollowUpQuest": 21,
    "QuestGiverID": 7,
    "QuestTurnInID": 7,
    "IsAchivement": 0,
    "Repeatable": 1,
    "IsDailyQuest": 0,
    "IsWeeklyQuest": 1,
    "CancelQuestOnPlayerDeath": 1,
    "Autocomplete": 0,
    "IsGroupQuest": 0,
    "IsBanditQuest": 0,
    "IsHeroQuest": 0,
    "ObjectSetFileName": "",
    "QuestClassName": "",
    "Objectives": [
        {
            "ConfigVersion": 4,
            "ID": 204,
            "ObjectiveType": 2,
            "ObjectiveText": "",
            "TimeLimit": -1
        }
    ],
    "QuestItems": [
        {
            "ClassName": "shovel",
            "Amount": 1
        }
    ],
    "Rewards": [
        {
            "ClassName": "TWP_Cosmetic_Scorpion",
            "Amount": 1
        },
        {
            "ClassName": "ExpansionGoldBar",
            "Amount": 1
        },
        {
            "ClassName": "MAD_Backpack_Black",
            "Amount": 1
        }
    ],
    "NeedToSelectReward": 0,
    "RewardsForGroupOwnerOnly": 1,
    "HumanityReward": 0
}